pyroscope/otel/__init__.py
pyroscope_otel-0.4.1.dist-info/licenses/LICENSE
pyroscope_otel-0.4.1.dist-info/METADATA
pyroscope_otel-0.4.1.dist-info/WHEEL
pyroscope_otel-0.4.1.dist-info/top_level.txt
pyroscope_otel-0.4.1.dist-info/RECORD
