Metadata-Version: 2.4
Name: pyroscope-otel
Version: 0.4.1
Summary: A library providing profiling functionalities related to OpenTelemetry
License:                                  Apache License
Requires-Python: >=3.8
License-File: LICENSE
Requires-Dist: opentelemetry-api<2.0.0,>=1.27.0
Requires-Dist: opentelemetry-sdk<2.0.0,>=1.27.0
Requires-Dist: pyroscope-io>=0.8.10
Dynamic: license-file
